{
  "circular_radial_n1": {
    "id": "circular_radial_n1",
    "shape": "circular",
    "slot_style": "radial",
    "label": "Circular Radial - 1 Section",
    "tooltip": "Circular Design - Radial Waveform\nOne Panel\n\nAvailable size:\n24 to 30 inch diameter.",
    "thumbnail": "/assets/style/thumbnails/circular_radial_n1.png",
    "number_sections": 1,
    "number_slots": 48,
    "separation": 0
  },
  "circular_radial_n2": {
    "id": "circular_radial_n2",
    "shape": "circular",
    "slot_style": "radial",
    "label": "Circular Radial - 2 Sections",
    "tooltip": "Circular Design - Radial Waveform\nTwo Panels\n\nAvailable size:\n24 to 42 inch diameter",
    "thumbnail": "/assets/style/thumbnails/circular_radial_n2.png",
    "number_sections": 2,
    "number_slots": 48,
    "separation": 2
  },
  "circular_radial_n3": {
    "id": "circular_radial_n3",
    "shape": "circular",
    "slot_style": "radial",
    "label": "Circular Radial - 3 Sections",
    "tooltip": "Circular Design - Radial Waveform\nThree Panels\n\nAvailable size:\n24 to 54 inch diameter",
    "thumbnail": "/assets/style/thumbnails/circular_radial_n3.png",
    "number_sections": 3,
    "number_slots": 48,
    "separation": 1.5
  },
  "circular_radial_n4": {
    "id": "circular_radial_n4",
    "shape": "circular",
    "slot_style": "radial",
    "label": "Circular Radial - 4 Sections",
    "tooltip": "Circular Design - Radial Waveform\nFour Panels\n\nAvailable size:\n24 to 60 inch diameter",
    "thumbnail": "/assets/style/thumbnails/circular_radial_n4.png",
    "number_sections": 4,
    "number_slots": 48,
    "separation": 1
  },
  "circular_linear_n1": {
    "id": "circular_linear_n1",
    "shape": "circular",
    "slot_style": "linear",
    "label": "Circular Linear - 1 Section",
    "tooltip": "Circular Design - Linear Waveform\nOne Panel\n\nAvailable size:\n24 to 30 inch diameter",
    "thumbnail": "/assets/style/thumbnails/circular_linear_n1.png",
    "number_sections": 1,
    "number_slots": 24,
    "separation": 0,
    "side_margin": 3
  },
  "circular_linear_n2": {
    "id": "circular_linear_n2",
    "shape": "circular",
    "slot_style": "linear",
    "label": "Circular Linear - 2 Sections",
    "tooltip": "Circular Design - Linear Waveform\nTwo Panels\n\nAvailable size:\n24 to 42 inch diameter",
    "thumbnail": "/assets/style/thumbnails/circular_linear_n2.png",
    "number_sections": 2,
    "number_slots": 24,
    "separation": 2,
    "side_margin": 3
  },
  "rectangular_radial_n1": {
    "id": "rectangular_radial_n1",
    "shape": "rectangular",
    "slot_style": "radial",
    "label": "Rectangular Radial - 1 Section",
    "tooltip": "This is a tooltip",
    "thumbnail": "/assets/style/thumbnails/rectangular_radial_n1.png",
    "number_sections": 1,
    "number_slots": 48,
    "separation": 0
  },
  "rectangular_radial_n2": {
    "id": "rectangular_radial_n2",
    "shape": "rectangular",
    "slot_style": "radial",
    "label": "Rectangular Radial - 2 Sections",
    "tooltip": "This is a tooltip",
    "thumbnail": "/assets/style/thumbnails/rectangular_radial_n2.png",
    "number_sections": 2,
    "number_slots": 48,
    "separation": 2
  },
  "rectangular_radial_n4": {
    "id": "rectangular_radial_n4",
    "shape": "rectangular",
    "slot_style": "radial",
    "label": "Rectangular Radial - 4 Sections",
    "tooltip": "This is a tooltip",
    "thumbnail": "/assets/style/thumbnails/rectangular_radial_n4.png",
    "number_sections": 4,
    "number_slots": 48,
    "separation": 1
  },
  "rectangular_linear_n1": {
    "id": "rectangular_linear_n1",
    "shape": "rectangular",
    "slot_style": "linear",
    "label": "Rectangular Linear - 1 Section",
    "tooltip": "This is a tooltip",
    "thumbnail": "/assets/style/thumbnails/rectangular_linear_n1.png",
    "number_sections": 1,
    "number_slots": 18,
    "separation": 0
  },
  "rectangular_linear_n2": {
    "id": "rectangular_linear_n2",
    "shape": "rectangular",
    "slot_style": "linear",
    "label": "Rectangular Linear - 2 Sections (Side-by-Side)",
    "tooltip": "This is a tooltip",
    "thumbnail": "/assets/style/thumbnails/rectangular_linear_n2.png",
    "number_sections": 2,
    "number_slots": 36,
    "separation": 2
  },
  "rectangular_linear_n3": {
    "id": "rectangular_linear_n3",
    "shape": "rectangular",
    "slot_style": "linear",
    "label": "Rectangular Linear - 3 Sections (Side-by-Side)",
    "tooltip": "This is a tooltip",
    "thumbnail": "/assets/style/thumbnails/rectangular_linear_n3.png",
    "number_sections": 3,
    "number_slots": 54,
    "separation": 2
  },
  "rectangular_linear_n4": {
    "id": "rectangular_linear_n4",
    "shape": "rectangular",
    "slot_style": "linear",
    "label": "Rectangular Linear - 4 Sections (Side-by-Side)",
    "tooltip": "This is a tooltip",
    "thumbnail": "/assets/style/thumbnails/rectangular_linear_n4.png",
    "number_sections": 4,
    "number_slots": 72,
    "separation": 2
  },
  "diamond_radial_n1": {
    "id": "diamond_radial_n1",
    "shape": "diamond",
    "slot_style": "radial",
    "label": "Diamond Radial - 1 Section",
    "tooltip": "This is a tooltip",
    "thumbnail": "/assets/style/thumbnails/diamond_radial_n1.png",
    "number_sections": 1,
    "number_slots": 48,
    "separation": 0
  },
  "diamond_radial_n2": {
    "id": "diamond_radial_n2",
    "shape": "diamond",
    "slot_style": "radial",
    "label": "Diamond Radial - 2 Sections",
    "tooltip": "This is a tooltip",
    "thumbnail": "/assets/style/thumbnails/diamond_radial_n2.png",
    "number_sections": 2,
    "number_slots": 48,
    "separation": 1.5
  },
  "diamond_radial_n4": {
    "id": "diamond_radial_n4",
    "shape": "diamond",
    "slot_style": "radial",
    "label": "Diamond Radial - 4 Sections",
    "tooltip": "This is a tooltip",
    "thumbnail": "/assets/style/thumbnails/diamond_radial_n4.png",
    "number_sections": 4,
    "number_slots": 48,
    "separation": 2
  },
  "diamond_linear_n1": {
    "id": "diamond_linear_n1",
    "shape": "diamond",
    "slot_style": "linear",
    "label": "Diamond Linear - 1 Section",
    "tooltip": "This is a tooltip",
    "thumbnail": "/assets/style/thumbnails/diamond_linear_n1.png",
    "number_sections": 1,
    "number_slots": 24,
    "separation": 0,
    "side_margin": 5
  },
  "diamond_linear_n2": {
    "id": "diamond_linear_n2",
    "shape": "diamond",
    "slot_style": "linear",
    "label": "Diamond Linear - 2 Sections",
    "tooltip": "This is a tooltip",
    "thumbnail": "/assets/style/thumbnails/diamond_linear_n2.png",
    "number_sections": 2,
    "number_slots": 24,
    "separation": 2,
    "side_margin": 5
  }
}